animal_breeding_optimizer/__init__.py
animal_breeding_optimizer-0.1.0.dist-info/licenses/LICENSE
animal_breeding_optimizer-0.1.0.dist-info/METADATA
animal_breeding_optimizer-0.1.0.dist-info/WHEEL
animal_breeding_optimizer-0.1.0.dist-info/top_level.txt
animal_breeding_optimizer-0.1.0.dist-info/RECORD
