Metadata-Version: 2.4
Name: animal_breeding_optimizer
Version: 0.1.0
Summary: Микро-библиотека для оптимизации разведения животных
Home-page: https://github.com/busheisha/animal_breeding_optimizer
Author: busheisha
License: MIT License
Project-URL: Homepage, https://github.com/busheisha/animal_breeding_optimizer
Requires-Python: >=3.7
License-File: LICENSE
Requires-Dist: pandas
Requires-Dist: numpy
Requires-Dist: networkx
Requires-Dist: deap
Dynamic: home-page
Dynamic: license-file
Dynamic: requires-python
